{
  "users": [
    {
      "id": 1,
      "full_name": "Adiana Ciciari",
      "email": "aciciari0@loc.gov",
      "password": "3Qk42uWa",
      "avatar": "https://robohash.org/utundenostrum.png?size=50x50&set=set1"
    },
    {
      "id": 2,
      "full_name": "Mickie Mc Kellen",
      "email": "mmc1@homestead.com",
      "password": "xLanMXv",
      "avatar": "https://robohash.org/enimetsint.png?size=50x50&set=set1"
    },
    {
      "id": 3,
      "full_name": "Raffarty Boik",
      "email": "rboik2@pagesperso-orange.fr",
      "password": "56r78d7",
      "avatar": "https://robohash.org/rerumdelenitivelit.png?size=50x50&set=set1"
    },
    {
      "id": 4,
      "full_name": "Jeffy Vasilkov",
      "email": "jvasilkov3@nydailynews.com",
      "password": "CXX79Wc6l",
      "avatar": "https://robohash.org/eumnihilodit.png?size=50x50&set=set1"
    },
    {
      "id": 5,
      "full_name": "Ravi Masters",
      "email": "rmasters4@is.gd",
      "password": "sOxJbVqD",
      "avatar": "https://robohash.org/accusamusvelautem.png?size=50x50&set=set1"
    },
    {
      "id": 6,
      "full_name": "Lindsey Gonnely",
      "email": "lgonnely5@360.cn",
      "password": "nLzpcdjKhNR",
      "avatar": "https://robohash.org/abdelenitineque.png?size=50x50&set=set1"
    },
    {
      "id": 7,
      "full_name": "Amalia Teideman",
      "email": "ateideman6@prnewswire.com",
      "password": "ZPJ8Tp2YUm",
      "avatar": "https://robohash.org/exfugaet.png?size=50x50&set=set1"
    },
    {
      "id": 8,
      "full_name": "Bobbie Spear",
      "email": "bspear7@senate.gov",
      "password": "uunaJaw",
      "avatar": "https://robohash.org/teneturvoluptatembeatae.png?size=50x50&set=set1"
    },
    {
      "id": 9,
      "full_name": "Oliviero Bramwich",
      "email": "obramwich8@businessinsider.com",
      "password": "yPF36ZcO",
      "avatar": "https://robohash.org/sedquiquibusdam.png?size=50x50&set=set1"
    },
    {
      "id": 10,
      "full_name": "Tildie Hindenberger",
      "email": "thindenberger9@blogs.com",
      "password": "q8VKBTgaxS",
      "avatar": "https://robohash.org/odioiustodelectus.png?size=50x50&set=set1"
    }
  ],

  "freedom_data" :[
    {
      "id": 1,
      "name": "Nicolas Yellowlee",
      "image": "https://img.freepik.com/free-photo/young-bearded-man-with-striped-shirt_273609-5677.jpg?w=2000",
      "gender": "Male",
      "country": "Sweden",
      "age": 16,
      "department": "student"
    },
    {
      "id": 2,
      "name": "Langston Place",
      "image": "https://img.freepik.com/free-photo/young-bearded-man-with-striped-shirt_273609-5677.jpg?w=2000",
      "gender": "Male",
      "country": "Czech Republic",
      "age": 20,
      "department": "employed"
    },
    {
      "id": 3,
      "name": "Edward List",
      "image": "https://img.freepik.com/free-photo/young-bearded-man-with-striped-shirt_273609-5677.jpg?w=2000",
      "gender": "Male",
      "country": "China",
      "age": 33,
      "department": "student"
    },
    {
      "id": 4,
      "name": "Pattie Moorerud",
      "image": "https://img.freepik.com/free-photo/young-bearded-man-with-striped-shirt_273609-5677.jpg?w=2000",
      "gender": "Male",
      "country": "China",
      "age": 24,
      "department": "employed"
    },
    {
      "id": 5,
      "name": "Noel Blakelock",
      "image": "https://img.freepik.com/free-photo/young-bearded-man-with-striped-shirt_273609-5677.jpg?w=2000",
      "gender": "Female",
      "country": "Russia",
      "age": 25,
      "department": "student"
    },
    {
      "id": 6,
      "name": "Towny Banbrigge",
      "image": "https://img.freepik.com/free-photo/young-bearded-man-with-striped-shirt_273609-5677.jpg?w=2000",
      "gender": "Male",
      "country": "Afghanistan",
      "age": 36,
      "department": "employed"
    },
    {
      "id": 7,
      "name": "Katerine Ashplant",
      "image": "https://img.freepik.com/free-photo/young-bearded-man-with-striped-shirt_273609-5677.jpg?w=2000",
      "gender": "Female",
      "country": "China",
      "age": 27,
      "department": "student"
    },
    {
      "id": 8,
      "name": "Bridget Hunnam",
      "image": "https://img.freepik.com/free-photo/young-bearded-man-with-striped-shirt_273609-5677.jpg?w=2000",
      "gender": "Female",
      "country": "Indonesia",
      "age": 38,
      "department": "employed"
    },
    {
      "id": 9,
      "name": "Kleon Mabey",
      "image": "https://img.freepik.com/free-photo/young-bearded-man-with-striped-shirt_273609-5677.jpg?w=2000",
      "gender": "Male",
      "country": "Mexico",
      "age": 19,
      "department": "student"
    },
    {
      "id": 10,
      "name": "Margo Mushrow",
      "image": "https://img.freepik.com/free-photo/young-bearded-man-with-striped-shirt_273609-5677.jpg?w=2000",
      "gender": "Female",
      "country": "Botswana",
      "age": 40,
      "department": "student"
    }
  ]
}